gslides_api/__init__.py
gslides_api/_version.py
gslides_api/agnostic/__init__.py
gslides_api/agnostic/converters.py
gslides_api/agnostic/domain.py
gslides_api/agnostic/element.py
gslides_api/agnostic/ir.py
gslides_api/agnostic/ir_to_markdown.py
gslides_api/agnostic/library.py
gslides_api/agnostic/markdown_parser.py
gslides_api/agnostic/presentation.py
gslides_api/agnostic/text.py
gslides_api/agnostic/units.py
gslides_api/client.py
gslides_api/domain/__init__.py
gslides_api/domain/domain.py
gslides_api/domain/request.py
gslides_api/domain/table.py
gslides_api/domain/table_cell.py
gslides_api/domain/text.py
gslides_api/element/__init__.py
gslides_api/element/base.py
gslides_api/element/element.py
gslides_api/element/image.py
gslides_api/element/shape.py
gslides_api/element/table.py
gslides_api/element/text_content.py
gslides_api/execute.py
gslides_api/json_diff.py
gslides_api/markdown/__init__.py
gslides_api/markdown/from_markdown.py
gslides_api/mcp/__init__.py
gslides_api/mcp/models.py
gslides_api/mcp/server.py
gslides_api/mcp/utils.py
gslides_api/page/__init__.py
gslides_api/page/base.py
gslides_api/page/notes.py
gslides_api/page/page.py
gslides_api/page/slide.py
gslides_api/page/slide_properties.py
gslides_api/presentation.py
gslides_api/presentation_to_library.py
gslides_api/py.typed
gslides_api/request/__init__.py
gslides_api/request/parent.py
gslides_api/request/request.py
gslides_api/request/reshape.py
gslides_api/request/table.py
gslides_api/response.py
gslides_api/utils.py
gslides_api-0.3.3.dist-info/LICENSE
gslides_api-0.3.3.dist-info/METADATA
gslides_api-0.3.3.dist-info/WHEEL
gslides_api-0.3.3.dist-info/entry_points.txt
gslides_api-0.3.3.dist-info/RECORD
