Metadata-Version: 2.3
Name: gslides-api
Version: 0.3.3
Summary: A Python library for working with Google Slides API using Pydantic domain objects
License: MIT
Author: motley.ai
Author-email: info@motley.ai
Requires-Python: >=3.11,<4.0
Classifier: License :: OSI Approved :: MIT License
Classifier: Programming Language :: Python :: 3
Classifier: Programming Language :: Python :: 3.11
Classifier: Programming Language :: Python :: 3.12
Classifier: Programming Language :: Python :: 3.13
Provides-Extra: image
Provides-Extra: tables
Requires-Dist: google-api-python-client (>=2.169.0,<3.0.0)
Requires-Dist: google-auth (>=2.0.0,<3.0.0)
Requires-Dist: google-auth-oauthlib (>=1.2.2,<2.0.0)
Requires-Dist: marko (>=2.1.4,<3.0.0)
Requires-Dist: mcp (>=1.0.0,<2.0.0)
Requires-Dist: pandas (>=2.0.0,<3.0.0) ; extra == "tables"
Requires-Dist: pillow (>=10.0.0,<11.0.0) ; extra == "image"
Requires-Dist: protobuf (>=6.31.1,<7.0.0)
Requires-Dist: pydantic (>=2.11.7,<3.0.0)
Requires-Dist: requests (>=2.32.4,<3.0.0)
Requires-Dist: typeguard (>=4.4.4,<5.0.0)
